darkstrata_credential_check/__init__.py
darkstrata_credential_check/client.py
darkstrata_credential_check/constants.py
darkstrata_credential_check/crypto.py
darkstrata_credential_check/errors.py
darkstrata_credential_check/py.typed
darkstrata_credential_check/types.py
darkstrata_credential_check-1.2.2.dist-info/METADATA
darkstrata_credential_check-1.2.2.dist-info/WHEEL
darkstrata_credential_check-1.2.2.dist-info/licenses/LICENSE
darkstrata_credential_check-1.2.2.dist-info/RECORD
