Metadata-Version: 2.4
Name: darkstrata-credential-check
Version: 1.2.2
Summary: Check if credentials have been exposed in data breaches using k-anonymity
Project-URL: Homepage, https://darkstrata.io
Project-URL: Documentation, https://github.com/darkstrata/darkstrata-sdks/blob/main/python/README.md
Project-URL: Repository, https://github.com/darkstrata/darkstrata-sdks
Project-URL: Issues, https://github.com/darkstrata/darkstrata-sdks/issues
Project-URL: Changelog, https://github.com/darkstrata/darkstrata-sdks/blob/main/python/CHANGELOG.md
Author-email: DarkStrata <support@darkstrata.io>
License: Apache-2.0
License-File: LICENSE
Keywords: breach,credentials,data-breach,k-anonymity,password,privacy,security
Classifier: Development Status :: 4 - Beta
Classifier: Intended Audience :: Developers
Classifier: License :: OSI Approved :: Apache Software License
Classifier: Operating System :: OS Independent
Classifier: Programming Language :: Python :: 3
Classifier: Programming Language :: Python :: 3.10
Classifier: Programming Language :: Python :: 3.11
Classifier: Programming Language :: Python :: 3.12
Classifier: Programming Language :: Python :: 3.13
Classifier: Topic :: Security
Classifier: Topic :: Software Development :: Libraries :: Python Modules
Classifier: Typing :: Typed
Requires-Python: >=3.10
Requires-Dist: httpx>=0.25.0
Provides-Extra: dev
Requires-Dist: mypy>=1.10.0; extra == 'dev'
Requires-Dist: pytest-asyncio>=0.23.0; extra == 'dev'
Requires-Dist: pytest-cov>=4.0.0; extra == 'dev'
Requires-Dist: pytest>=8.0.0; extra == 'dev'
Requires-Dist: respx>=0.21.0; extra == 'dev'
Requires-Dist: ruff>=0.4.0; extra == 'dev'
